triton_runner/README.md
triton_runner/__init__.py
triton_runner/autotune.py
triton_runner/check_utils.py
triton_runner/color_print.py
triton_runner/compile.py
triton_runner/dump_utils.py
triton_runner/jit.py
triton_runner/pass_stages.py
triton_runner/testing.py
triton_runner/torch_utils.py
triton_runner/version_utils.py
triton_runner/bench/__init__.py
triton_runner/bench/utils.py
triton_runner/bench/attn/attention_utils.py
triton_runner/bench/attn/triton_fused_attention.py
triton_runner/bench/launch_latency/__init__.py
triton_runner/bench/launch_latency/kernels.py
triton_runner/bench/matmul/__init__.py
triton_runner/bench/matmul/kernels.py
triton_runner/compiler/__init__.py
triton_runner/compiler/compiler.py
triton_runner/driver/__init__.py
triton_runner/driver/v3_5_0/__init__.py
triton_runner/driver/v3_5_0/driver.py
triton_runner/gluon_runner/__init__.py
triton_runner/gluon_runner/_runtime.py
triton_runner/language/__init__.py
triton_runner/language/dump.py
triton_runner/language/dump_before_3_4_0.py
triton_runner-0.3.3.dist-info/licenses/LICENSE
triton_runner-0.3.3.dist-info/METADATA
triton_runner-0.3.3.dist-info/WHEEL
triton_runner-0.3.3.dist-info/top_level.txt
triton_runner-0.3.3.dist-info/RECORD
