Metadata-Version: 2.4
Name: triton-runner
Version: 0.3.3
Summary: Multi-Level Triton Runner supporting Python, IR, PTX, and cubin.
Author-email: Bob Huang <x@bobhuang.xyz>
License-Expression: MIT
Project-URL: repository, https://github.com/toyaix/triton-runner
Project-URL: homepage, https://triton-runner.org
License-File: LICENSE
Requires-Dist: triton>=3.0.0
Requires-Dist: termcolor
Dynamic: license-file
